carbonia/__init__.py
carbonia/embeddings.py
carbonia/match.py
carbonia/utils.py
carbonia-0.1.0.dist-info/LICENSE
carbonia-0.1.0.dist-info/METADATA
carbonia-0.1.0.dist-info/WHEEL
carbonia-0.1.0.dist-info/entry_points.txt
carbonia-0.1.0.dist-info/top_level.txt
carbonia-0.1.0.dist-info/RECORD
